MANIFEST.in
setup.py
bdaq/__init__.py
bdaq/wrapper.cpp
bdaq/wrapper.pyx
bdaq/wrapper_enums.cpp
bdaq/wrapper_enums.pyx
bdaq/examples/__init__.py
bdaq/examples/ai_instant.py
bdaq/examples/do_static.py
bdaq/tools/__init__.py
bdaq/tools/extract_enums.py
pybdaq.egg-info/PKG-INFO
pybdaq.egg-info/SOURCES.txt
pybdaq.egg-info/dependency_links.txt
pybdaq.egg-info/top_level.txt