Metadata-Version: 1.1
Name: pybdaq
Version: 0.0.6
Summary: data acquisition hardware (DAQ) SDK wrapper
Home-page: http://github.com/angaza/pybdaq
Author: Angaza Design
Author-email: bcs@angazadesign.com
License: MIT
Keywords: daq wrapper library bionic advantech usb
Platform: UNKNOWN
Classifier: License :: OSI Approved :: MIT License
Classifier: Development Status :: 3 - Alpha
Classifier: Programming Language :: Cython
Classifier: Programming Language :: Python :: 2.7
Classifier: Operating System :: POSIX :: Linux
Classifier: Topic :: Utilities
Classifier: Topic :: System :: Hardware
Classifier: Topic :: Software Development :: Libraries
